setup.py
dozens/__init__.py
dozens/dozens.py
dozens/models.py
dozens.egg-info/PKG-INFO
dozens.egg-info/SOURCES.txt
dozens.egg-info/dependency_links.txt
dozens.egg-info/top_level.txt
tests/__init__.py
tests/test_dozens.py