Metadata-Version: 1.1
Name: dozens
Version: 0.0.3
Summary: Wrapper for Dozens API
Home-page: UNKNOWN
Author: mikamix
Author-email: tmp@mikamix.net
License: MIT
Keywords: dozens
Platform: UNKNOWN
Classifier: Development Status :: 4 - Beta
Classifier: Intended Audience :: Developers
Classifier: License :: OSI Approved :: MIT License
Classifier: Programming Language :: Python
